pyobf/__init__.py
pyobf/__main__.py
pyobf/cli.py
pyobf/obfuscator.py
pyobf-0.1.1.dist-info/METADATA
pyobf-0.1.1.dist-info/WHEEL
pyobf-0.1.1.dist-info/entry_points.txt
pyobf-0.1.1.dist-info/licenses/LICENSE
pyobf-0.1.1.dist-info/RECORD
